django_honeyguard/__init__.py
django_honeyguard/admin.py
django_honeyguard/apps.py
django_honeyguard/conf.py
django_honeyguard/constants.py
django_honeyguard/forms.py
django_honeyguard/handlers.py
django_honeyguard/loggers.py
django_honeyguard/models.py
django_honeyguard/services.py
django_honeyguard/signals.py
django_honeyguard/urls.py
django_honeyguard/utils.py
django_honeyguard/views.py
django_honeyguard/locale/ar/LC_MESSAGES/django.mo
django_honeyguard/locale/ar/LC_MESSAGES/django.po
django_honeyguard/locale/be/LC_MESSAGES/django.mo
django_honeyguard/locale/be/LC_MESSAGES/django.po
django_honeyguard/locale/bg/LC_MESSAGES/django.mo
django_honeyguard/locale/bg/LC_MESSAGES/django.po
django_honeyguard/locale/cs/LC_MESSAGES/django.mo
django_honeyguard/locale/cs/LC_MESSAGES/django.po
django_honeyguard/locale/da/LC_MESSAGES/django.mo
django_honeyguard/locale/da/LC_MESSAGES/django.po
django_honeyguard/locale/de/LC_MESSAGES/django.mo
django_honeyguard/locale/de/LC_MESSAGES/django.po
django_honeyguard/locale/el/LC_MESSAGES/django.mo
django_honeyguard/locale/el/LC_MESSAGES/django.po
django_honeyguard/locale/es/LC_MESSAGES/django.mo
django_honeyguard/locale/es/LC_MESSAGES/django.po
django_honeyguard/locale/fa/LC_MESSAGES/django.mo
django_honeyguard/locale/fa/LC_MESSAGES/django.po
django_honeyguard/locale/fi/LC_MESSAGES/django.mo
django_honeyguard/locale/fi/LC_MESSAGES/django.po
django_honeyguard/locale/fr/LC_MESSAGES/django.mo
django_honeyguard/locale/fr/LC_MESSAGES/django.po
django_honeyguard/locale/hi/LC_MESSAGES/django.mo
django_honeyguard/locale/hi/LC_MESSAGES/django.po
django_honeyguard/locale/id/LC_MESSAGES/django.mo
django_honeyguard/locale/id/LC_MESSAGES/django.po
django_honeyguard/locale/it/LC_MESSAGES/django.mo
django_honeyguard/locale/it/LC_MESSAGES/django.po
django_honeyguard/locale/ja/LC_MESSAGES/django.mo
django_honeyguard/locale/ja/LC_MESSAGES/django.po
django_honeyguard/locale/ko/LC_MESSAGES/django.mo
django_honeyguard/locale/ko/LC_MESSAGES/django.po
django_honeyguard-1.0.0.dist-info/METADATA
django_honeyguard-1.0.0.dist-info/WHEEL
django_honeyguard-1.0.0.dist-info/licenses/LICENSE
django_honeyguard-1.0.0.dist-info/RECORD
