Metadata-Version: 2.4
Name: django-honeyguard
Version: 1.0.0
Summary: Reusable Django app providing multi-CMS honeypot login traps with DB logging and email alerts.
Project-URL: Homepage, https://github.com/alihtt/django-honeyguard/tree/main
Project-URL: Documentation, https://django-honeyguard.readthedocs.io/en/main/
Project-URL: Changelog, https://github.com/alihtt/django-honeyguard/blob/main/CHANGES.rst
Project-URL: Bug Tracker, https://github.com/alihtt/django-honeyguard/issues
Project-URL: Source Code, https://github.com/alihtt/django-honeyguard
Author-email: Ali Hatami <aliht.workspace@gmail.com>
License: BSD
License-File: LICENSE
Keywords: admin,django,honeypot,security,wordpress,wp-admin
Classifier: Development Status :: 3 - Alpha
Classifier: Environment :: Web Environment
Classifier: Framework :: Django
Classifier: Framework :: Django :: 4.2
Classifier: Framework :: Django :: 5.0
Classifier: Framework :: Django :: 5.1
Classifier: Framework :: Django :: 5.2
Classifier: Intended Audience :: Developers
Classifier: License :: OSI Approved :: BSD License
Classifier: Programming Language :: Python
Classifier: Programming Language :: Python :: 3
Classifier: Programming Language :: Python :: 3 :: Only
Classifier: Programming Language :: Python :: 3.10
Classifier: Programming Language :: Python :: 3.11
Classifier: Programming Language :: Python :: 3.12
Classifier: Topic :: Security
Requires-Python: >=3.10
Requires-Dist: django>=5.0
